mumuzi/LSB.py
mumuzi/__init__.py
mumuzi/banners.py
mumuzi/mumuzi.py
mumuzi/tao_func.py
mumuzi/taoshenyulu.py
mumuzi/xuan.py
mumuzi/xuan_func.py
mumuzi/modules/__init__.py
mumuzi/modules/misc/__init__.py
mumuzi/modules/misc/ctfshow_cjb_Zipper.py
mumuzi/modules/misc/ctfshow_jwb_GameProRev.py
mumuzi/modules/misc/ctfshow_jwb_QuestOfImage.py
mumuzi/modules/misc/ctfshow_yrb22_brainfix.py
mumuzi/modules/web/__init__.py
mumuzi/modules/web/ctfshow_blb_webqiandao.py
mumuzi/modules/web/ctfshow_jwb_EasyUnserialize.py
mumuzi/modules/web/ctfshow_webrumen_web680.py
mumuzi/riposte/__init__.py
mumuzi/riposte/_version.py
mumuzi/riposte/command.py
mumuzi/riposte/exceptions.py
mumuzi/riposte/guides.py
mumuzi/riposte/input_streams.py
mumuzi/riposte/riposte.py
mumuzi/riposte/printer/__init__.py
mumuzi/riposte/printer/mixins.py
mumuzi/riposte/printer/palette.py
mumuzi/riposte/printer/thread.py
mumuzi-1.2.3.dist-info/METADATA
mumuzi-1.2.3.dist-info/WHEEL
mumuzi-1.2.3.dist-info/top_level.txt
mumuzi-1.2.3.dist-info/RECORD
