Metadata-Version: 2.1
Name: mumuzi
Version: 1.2.3
Summary: ctf全栈全自动解题姬mumuzi
Home-page: https://blog.csdn.net/qq_42880719/
Author: Neuron-Network on Mumuzi
Author-email: mumuzi@mumuzi.mumuzi
License: UNKNOWN
Project-URL: Bug Tracker, https://blog.csdn.net/qq_42880719/
Platform: UNKNOWN
Classifier: Programming Language :: Python :: 3
Classifier: License :: OSI Approved :: MIT License
Classifier: Operating System :: OS Independent
Requires-Python: >=3.6
Requires-Dist: pyreadline
Requires-Dist: colorama
Requires-Dist: pillow
Requires-Dist: pwntools
